minbc_lib/__init__.py
minbc_lib/bcipher.py
minbc_lib/caesar.py
minbc_lib/ecc.py
minbc_lib/enigma.py
minbc_lib/hash.py
minbc_lib/hashchain.py
minbc_lib/lfreq.py
minbc_lib/markttree.py
minbc_lib/rsa.py
minbc_lib/ssc.py
minbc_lib/dwwallets/__init__.py
minbc_lib/dwwallets/dwwallets.py
minbc_lib/dwwallets/plist_a.py
minbc_lib/dwwallets/plist_b.py
minbc_lib/dwwallets/plist_c.py
minbc_lib/pyenigma/__init__.py
minbc_lib/pyenigma/enigma.py
minbc_lib/pyenigma/rotor.py
minbc_lib-0.22b0.dist-info/METADATA
minbc_lib-0.22b0.dist-info/RECORD
minbc_lib-0.22b0.dist-info/WHEEL
minbc_lib-0.22b0.dist-info/entry_points.txt
minbc_lib-0.22b0.dist-info/top_level.txt
