Metadata-Version: 2.1
Name: minbc-lib
Version: 0.22b0
Summary: Package Dependency: Validates package requirements
Home-page: https://github.com/shibats/minbc_lib
Author: ats
Author-email: shibata@m-info.co.jp
Maintainer: ats
Maintainer-email: shibata@m-info.co.jp
License: MIT
Platform: UNKNOWN
Classifier: Programming Language :: Python :: 3.7
Classifier: License :: OSI Approved :: MIT License
Requires-Dist: pyenigma
